_pyvconf/__init__.py
_pyvconf/iniparser.py
_pyvconf/iniparser_test.py
_pyvconf/parser.py
_pyvconf/parser_test.py
_pyvconf/py.typed
_pyvconf/sectionparser.py
_pyvconf/sectionparser_test.py
_pyvconf/types.py
pyvconf/__init__.py
pyvconf/py.typed
pyvconf-0.0.1.dist-info/METADATA
pyvconf-0.0.1.dist-info/WHEEL
pyvconf-0.0.1.dist-info/top_level.txt
pyvconf-0.0.1.dist-info/RECORD
